labneura.cpython-39-darwin.so
labneura2-0.2.6.dist-info/licenses/LICENSE
labneura2-0.2.6.dist-info/METADATA
labneura2-0.2.6.dist-info/WHEEL
labneura2-0.2.6.dist-info/top_level.txt
labneura2-0.2.6.dist-info/RECORD
