Metadata-Version: 2.4
Name: labneura2
Version: 0.2.6
Summary: SIMD-accelerated tensor operations for neural networks
Home-page: https://github.com/gokatharun/LabNeura
Author: LabNeura Authors
Author-email: 
License: MIT
Classifier: Programming Language :: Python :: 3
Classifier: Programming Language :: C++
Classifier: License :: OSI Approved :: MIT License
Classifier: Operating System :: MacOS
Classifier: Operating System :: POSIX :: Linux
Classifier: Topic :: Scientific/Engineering :: Artificial Intelligence
License-File: LICENSE
Dynamic: author
Dynamic: classifier
Dynamic: description
Dynamic: description-content-type
Dynamic: home-page
Dynamic: license
Dynamic: license-file
Dynamic: summary
